[{"_path":"/dir/moshes_law_pc","_dir":"dir","_draft":false,"_partial":false,"_locale":"","title":"Moshes Law P.C.","description":"Expert legal guidance in corporate law, real estate, employment discrimination, and personal injury, with specialized calculators for NYC financial clarity.","featured":false,"invert":false,"card_image":"LOYM-600x400-1-1.png","tags":["Contract Drafting","Bankruptcy Guidance","Estate Planning","Employment Litigation","Real Estate Law"],"_type":"markdown","_id":"content:dir:Moshes_Law_PC.md","_source":"content","_file":"dir/Moshes_Law_PC.md","_stem":"dir/Moshes_Law_PC","_extension":"md","sitemap":{"loc":"/dir/moshes_law_pc"}},{"_path":"/dir/pearson_butler","_dir":"dir","_draft":false,"_partial":false,"_locale":"","title":"Pearson Butler","description":"Expert legal guidance for Utah corporations, specializing in complex financial and tax planning.","featured":false,"invert":false,"card_image":"Logo_5.png","tags":["Start-Up Legal Services","Corporate Governance","Family Business Law","Contract Drafting","Bankruptcy Guidance","Intellectual Property","Compliance and Regulation","Taxation Advice","Small Business Support","Estate Planning","Employment Litigation","Real Estate Law","Business Disputes"],"_type":"markdown","_id":"content:dir:Pearson_Butler.md","_source":"content","_file":"dir/Pearson_Butler.md","_stem":"dir/Pearson_Butler","_extension":"md","sitemap":{"loc":"/dir/pearson_butler"}}]