[{"_path":"/blog/essential_tax_tips_corporate_lawyers_mergers_acquisitions","_dir":"blog","_draft":false,"_partial":false,"_locale":"","title":"5 Essential Tax Tips for Corporate Lawyers Navigating Mergers and Acquisitions","description":"Corporate lawyers engaged in mergers and acquisitions (M&A) face intricate challenges, not least of which involve taxation. At Georgetown Law, the importance of tax knowledge in structuring deals is underscored, highlighting the necessity for corporate lawyers to have a firm grasp on tax issues to optimize their clients' financial outcomes. Here are five essential tax tips for corporate lawyers delving into M&A, designed to sharpen their strategic edge:","_type":"markdown","_id":"content:blog:essential_tax_tips_corporate_lawyers_mergers_acquisitions.md","_source":"content","_file":"blog/essential_tax_tips_corporate_lawyers_mergers_acquisitions.md","_stem":"blog/essential_tax_tips_corporate_lawyers_mergers_acquisitions","_extension":"md","sitemap":{"loc":"/blog/essential_tax_tips_corporate_lawyers_mergers_acquisitions"}},{"_path":"/blog/estate_planning_insights_for_businesses_key_considerations","_dir":"blog","_draft":false,"_partial":false,"_locale":"","title":"Estate Planning Insights for Businesses: Key Considerations to Avoid Pitfalls","description":"Estate planning can be a complex process, especially for business owners who need to ensure that their personal and professional assets are protected and transferred according to their wishes. This article highlights key considerations and common pitfalls business owners should be aware of when undertaking estate planning to avoid unnecessary complications and ensure a smooth transition of their business and assets.","_type":"markdown","_id":"content:blog:estate_planning_insights_for_businesses_key_considerations.md","_source":"content","_file":"blog/estate_planning_insights_for_businesses_key_considerations.md","_stem":"blog/estate_planning_insights_for_businesses_key_considerations","_extension":"md","sitemap":{"loc":"/blog/estate_planning_insights_for_businesses_key_considerations"}}]